test_bob8gook.py
testbob8gook.py
testbob8gook-1.0.0.14.dist-info/METADATA
testbob8gook-1.0.0.14.dist-info/WHEEL
testbob8gook-1.0.0.14.dist-info/top_level.txt
testbob8gook-1.0.0.14.dist-info/RECORD
